yukiiiii_tools/__init__.py
yukiiiii_tools/calculate.py
yukiiiii_tools/visulize.py
yukiiiii_tools-0.0.2.dist-info/LICENSE
yukiiiii_tools-0.0.2.dist-info/METADATA
yukiiiii_tools-0.0.2.dist-info/WHEEL
yukiiiii_tools-0.0.2.dist-info/top_level.txt
yukiiiii_tools-0.0.2.dist-info/RECORD
