Metadata-Version: 2.1
Name: yukiiiii_tools
Version: 0.0.2
Summary: My basic but custo library
Author-email: Yuk Hu <873933169@qq.com>
Project-URL: Homepage, https://github.com/Mech-Who/Yukiiiii_tools
Project-URL: Issues, https://github.com/Mech-Who/Yukiiiii_tools/issues
Classifier: Intended Audience :: Developers
Classifier: Operating System :: OS Independent
Classifier: Natural Language :: Chinese (Simplified)
Classifier: Programming Language :: Python
Classifier: Programming Language :: Python :: 3
Classifier: Topic :: Software Development :: Libraries
Requires-Python: >=3.8
License-File: LICENSE
Requires-Dist: netron
